pebm/MANIFEST.in
pebm/Preprocessing.py
pebm/_ErrorHandler.py
pebm/_init_.py
pebm/_version.py
pebm/main.py
pebm/pyproject.toml
pebm/tox.ini
pebm/ebm/Biomarkers.py
pebm/ebm/FiducialPoints.py
pebm/ebm/IntervalsDuration.py
pebm/ebm/Statistics.py
pebm/ebm/WavesCharacteristics.py
pebm/ebm/__init__.py
pebm/ebm/demo.py
pebm/ebm/fecgyn_tgen.py
pebm/ebm/setup.py
pebm/ebm/skeleton.py
pebm/ebm/c_files/00README
pebm/ebm/c_files/A00001_ecg_epltd.dat
pebm/ebm/c_files/A00001_ecg_epltd.epltd0
pebm/ebm/c_files/A00001_ecg_epltd.hea
pebm/ebm/c_files/EpltdAll.py
pebm/ebm/c_files/Makefile
pebm/ebm/c_files/Makefile_bak
pebm/ebm/c_files/_init_.py
pebm/ebm/c_files/analbeat.c
pebm/ebm/c_files/analbeat.h
pebm/ebm/c_files/analbeat.o
pebm/ebm/c_files/bdac.c
pebm/ebm/c_files/bdac.h
pebm/ebm/c_files/bdac.h.gch
pebm/ebm/c_files/bdac.o
pebm/ebm/c_files/bxbep
pebm/ebm/c_files/bxbep.c
pebm/ebm/c_files/classify.c
pebm/ebm/c_files/classify.o
pebm/ebm/c_files/easytest.c
pebm/ebm/c_files/easytest2
pebm/ebm/c_files/easytest_mimic2.c
pebm/ebm/c_files/epltd_all
pebm/ebm/c_files/epltd_all.c
pebm/ebm/c_files/epltd_all.o
pebm/ebm/c_files/epltd_all_oldjuly31_2013.c
pebm/ebm/c_files/epltd_ecgall_mimic2.c
pebm/ebm/c_files/epltd_wqrs_sqi_10s.c
pebm/ebm/c_files/epltd_wqrs_sqi_beatbybeat.c
pebm/ebm/c_files/hrvscript
pebm/ebm/c_files/index.html
pebm/ebm/c_files/inputs.h
pebm/ebm/c_files/match.c
pebm/ebm/c_files/match.h
pebm/ebm/c_files/match.o
pebm/ebm/c_files/mykurtosis.c
pebm/ebm/c_files/noisechk.c
pebm/ebm/c_files/noisechk.o
pebm/ebm/c_files/peak_det
pebm/ebm/c_files/peak_det.exe
pebm/ebm/c_files/peaks.txt
pebm/ebm/c_files/postclas.c
pebm/ebm/c_files/postclas.h
pebm/ebm/c_files/postclas.o
pebm/ebm/c_files/qrsdet.c
pebm/ebm/c_files/qrsdet.h
pebm/ebm/c_files/qrsdet.o
pebm/ebm/c_files/qrsdet2.c
pebm/ebm/c_files/qrsdet2.o
pebm/ebm/c_files/qrsfilt.c
pebm/ebm/c_files/qrsfilt.o
pebm/ebm/c_files/run_peak_det.sh
pebm/ebm/c_files/rythmchk.c
pebm/ebm/c_files/rythmchk.h
pebm/ebm/c_files/rythmchk.o
pebm/ebm/c_files/signal.txt
pebm-1.1.3.dist-info/AUTHORS.rst
pebm-1.1.3.dist-info/LICENSE.txt
pebm-1.1.3.dist-info/METADATA
pebm-1.1.3.dist-info/WHEEL
pebm-1.1.3.dist-info/top_level.txt
pebm-1.1.3.dist-info/RECORD
